setup.py
shinkenplugins/__init__.py
shinkenplugins.plugins.drupal_database.egg-info/PKG-INFO
shinkenplugins.plugins.drupal_database.egg-info/SOURCES.txt
shinkenplugins.plugins.drupal_database.egg-info/dependency_links.txt
shinkenplugins.plugins.drupal_database.egg-info/entry_points.txt
shinkenplugins.plugins.drupal_database.egg-info/namespace_packages.txt
shinkenplugins.plugins.drupal_database.egg-info/requires.txt
shinkenplugins.plugins.drupal_database.egg-info/top_level.txt
shinkenplugins/plugins/__init__.py
shinkenplugins/plugins/drupal_database/__init__.py
shinkenplugins/plugins/drupal_database/drupal_database.py